ProfanityDetector/__init__.py
ProfanityDetector/detector.py
ProfanityDetector/helpers.py
ProfanityDetector-0.2.dist-info/LICENSE
ProfanityDetector-0.2.dist-info/METADATA
ProfanityDetector-0.2.dist-info/WHEEL
ProfanityDetector-0.2.dist-info/top_level.txt
ProfanityDetector-0.2.dist-info/RECORD
